{
"version":"android-12.0",
"filename":"PixelExperience_Daredevil-12.1-20220524-0914-UNOFFICIAL.zip",
"datetime":1653383540,
"size":1396589439,
"url":"http://18.222.187.171:3000/roms/PixelExperience_Daredevil-12.1-20220524-0914-UNOFFICIAL.zip",
"filehash":"faa16334d5cab646f664f28eaea77f3b",
"id":"b0e785d7ee87a04e54acefa684a0554fe8f41385bbb413cf972dbb2d3d3ccef8",
"whatsNew":"- Improved system stability\n- User interface enhancements\n- Google Security Patch 2022-05",
"notification":"New PixelExperience Update"
}
